.noseids
bigml/chronos/__init__.py
bigml/chronos/chronos.py
bigml/chronos/formats.py
bigml/chronos/util.py
bigml/chronos/__pycache__/__init__.cpython-37.pyc
bigml/chronos/tests/__init__.py
bigml/chronos/tests/test_chronos.py
bigml/chronos/tests/__pycache__/__init__.cpython-37.pyc
bigml/chronos/tests/__pycache__/test_chronos.cpython-37.pyc
bigml_chronos.egg-info/PKG-INFO
bigml_chronos.egg-info/SOURCES.txt
bigml_chronos.egg-info/dependency_links.txt
bigml_chronos.egg-info/requires.txt
bigml_chronos.egg-info/top_level.txt
bigml_chronos-0.3.5.dist-info/LICENSE
bigml_chronos-0.3.5.dist-info/METADATA
bigml_chronos-0.3.5.dist-info/WHEEL
bigml_chronos-0.3.5.dist-info/top_level.txt
bigml_chronos-0.3.5.dist-info/RECORD
