Metadata-Version: 2.1
Name: bigml-chronos
Version: 0.3.5
Summary: Utilities for parsing time strings
Home-page: https://bigml.com
Author: The BigML Team
Author-email: bigml@bigml.com
License: http://www.apache.org/licenses/LICENSE-2.0
Download-URL: https://github.com/bigmlcom/chronos
Platform: UNKNOWN
Classifier: Development Status :: 4 - Beta
Classifier: Intended Audience :: Developers
Classifier: License :: OSI Approved :: Apache Software License
Classifier: Natural Language :: English
Classifier: Operating System :: OS Independent
Classifier: Programming Language :: Python
Classifier: Programming Language :: Python :: 2.7
Classifier: Programming Language :: Python :: 3
Classifier: Topic :: Software Development :: Libraries :: Python Modules
Requires-Python: >=2.7
Requires-Dist: isoweek
Requires-Dist: pytz
